twemoji_api
