Metadata-Version: 2.1
Name: twemoji-api
Version: 1.0.1
Summary: A lightweight utility for resolving emojis into file names, local asset paths, and URLs.
Author-email: Gustavo Pedroso Bernardes <gpedrosobernardes@gmail.com>
Project-URL: Homepage, https://github.com/gpedrosobernardes/twemoji_api
Project-URL: Source, https://github.com/gpedrosobernardes/twemoji_api
Project-URL: Issues, https://github.com/gpedrosobernardes/twemoji_api/issues
Requires-Python: >=3.8
License-File: LICENSE
Requires-Dist: pydantic
Requires-Dist: emojis
